nicegui_book_list/__init__.py
nicegui_book_list/main.py
nicegui_book_list/models.py
nicegui_book_list/py.typed
nicegui_book_list/ui.py
nicegui_book_list-0.1.1.dist-info/METADATA
nicegui_book_list-0.1.1.dist-info/WHEEL
nicegui_book_list-0.1.1.dist-info/entry_points.txt
nicegui_book_list-0.1.1.dist-info/licenses/LICENSE
nicegui_book_list-0.1.1.dist-info/RECORD
