Metadata-Version: 2.4
Name: nicegui-book-list
Version: 0.1.1
Summary: Book list sample application on tortoise database
Project-URL: docs, https://saitotsutomu.github.io/nicegui-book_list/
Project-URL: homepage, https://github.com/SaitoTsutomu/nicegui-book_list
Author-email: Saito Tsutomu <tsutomu7@hotmail.co.jp>
License-File: LICENSE
Classifier: Development Status :: 1 - Planning
Classifier: License :: OSI Approved :: Apache Software License
Classifier: Programming Language :: Python
Classifier: Topic :: Scientific/Engineering
Classifier: Topic :: Software Development
Requires-Python: >=3.12
Requires-Dist: fire>=0.7.0
Requires-Dist: nicegui>=2.11.1
Requires-Dist: pytest>=8.3.4
Requires-Dist: tortoise-orm>=0.24.0
